knight_dialer/__init__.py
knight_dialer/main.py
knight_dialer/version.py
knight_dialer-0.0.2.dist-info/LICENSE.txt
knight_dialer-0.0.2.dist-info/METADATA
knight_dialer-0.0.2.dist-info/WHEEL
knight_dialer-0.0.2.dist-info/top_level.txt
knight_dialer-0.0.2.dist-info/RECORD
