Metadata-Version: 2.1
Name: knight-dialer
Version: 0.0.2
Summary: An example of how to solve branching problems in two different ways
Home-page: https://github.com/NGeorgescu/knight_dialer
Author: NGeorgescu
Author-email: nsgeorgescu@gmail.com
License: see LICENSE.txt
Keywords: knight dialer chess knight recursive abstract data structure interview question problem
Platform: UNKNOWN
